cgsmiles/__init__.py
cgsmiles/cgsmiles_utils.py
cgsmiles/coordinates.py
cgsmiles/dialects.py
cgsmiles/drawing.py
cgsmiles/drawing_utils.py
cgsmiles/graph_layout.py
cgsmiles/graph_layout_utils.py
cgsmiles/graph_utils.py
cgsmiles/linalg_functions.py
cgsmiles/pysmiles_utils.py
cgsmiles/rdkit.py
cgsmiles/read_cgsmiles.py
cgsmiles/read_fragments.py
cgsmiles/resolve.py
cgsmiles/sample.py
cgsmiles/test_utils.py
cgsmiles/write_cgsmiles.py
cgsmiles/tests/test_cgsmile_parsing.py
cgsmiles/tests/test_coordinates.py
cgsmiles/tests/test_layering.py
cgsmiles/tests/test_molecule_resolve.py
cgsmiles/tests/test_rdkit.py
cgsmiles/tests/test_sampler.py
cgsmiles/tests/test_utils.py
cgsmiles/tests/test_write_cgsmiles.py
cgsmiles-1.0.1.dist-info/licenses/AUTHORS
cgsmiles-1.0.1.dist-info/licenses/LICENSE
cgsmiles-1.0.1.dist-info/METADATA
cgsmiles-1.0.1.dist-info/WHEEL
cgsmiles-1.0.1.dist-info/pbr.json
cgsmiles-1.0.1.dist-info/top_level.txt
cgsmiles-1.0.1.dist-info/RECORD
