Metadata-Version: 2.4
Name: cgsmiles
Version: 1.0.1
Home-page: https://github.com/gruenewald-lab/CGsmiles
Author: Fabian Grunewald
Author-email: fgrunewald.science@gmail.com
License: undefined
Keywords: smiles bigsmiles coarse-grained graphs line notation
Classifier: Development Status :: 5 - Production/Stable
Classifier: Environment :: Console
Classifier: Intended Audience :: Developers
Classifier: Intended Audience :: Science/Research
Classifier: License :: OSI Approved :: Apache Software License
Classifier: Operating System :: OS Independent
Classifier: Programming Language :: Python :: 3
Classifier: Programming Language :: Python :: 3.8
Classifier: Programming Language :: Python :: 3.9
Classifier: Programming Language :: Python :: 3.10
Classifier: Programming Language :: Python :: 3.11
Classifier: Topic :: Scientific/Engineering :: Bio-Informatics
Classifier: Topic :: Scientific/Engineering :: Chemistry
License-File: LICENSE
License-File: AUTHORS
Requires-Dist: pbr
Requires-Dist: numpy
Requires-Dist: networkx>=2.0
Requires-Dist: pysmiles
Dynamic: author
Dynamic: author-email
Dynamic: classifier
Dynamic: description
Dynamic: description-content-type
Dynamic: keywords
Dynamic: license
Dynamic: license-file
